GPIOEmulator/EmulatorGUI.py
GPIOEmulator/PIN.py
GPIOEmulator/TypeChecker.py
GPIOEmulator/__init__.py
GPIOEmulator/example.py
GPIOEmulator-1.1.2.dist-info/DESCRIPTION.rst
GPIOEmulator-1.1.2.dist-info/METADATA
GPIOEmulator-1.1.2.dist-info/RECORD
GPIOEmulator-1.1.2.dist-info/WHEEL
GPIOEmulator-1.1.2.dist-info/metadata.json
GPIOEmulator-1.1.2.dist-info/top_level.txt
