Metadata-Version: 2.1
Name: GPIOEmulator
Version: 1.1.2
Summary: This package was made with pip-boilerplate
Home-page: https://github.com/codenio/
Author: Aananth K
Author-email: aananthraj1995@gmail.com
License: GPL-3.0
Platform: UNKNOWN
